README.md
setup.py
simplogger/__init__.py
simplogger/logger.py
simplogger/run_test.py
simplogger.egg-info/PKG-INFO
simplogger.egg-info/SOURCES.txt
simplogger.egg-info/dependency_links.txt
simplogger.egg-info/top_level.txt