Metadata-Version: 2.1
Name: simplogger
Version: 0.2.1
Summary: Simple Logging Wrapper
Home-page: https://github.com/StephenMal/simplog
Author: Stephen Maldonado
Author-email: simplog@stephenmal.com
License: UNKNOWN
Platform: UNKNOWN
Classifier: Development Status :: 1 - Planning
Classifier: Programming Language :: Python :: 3 :: Only
Classifier: Topic :: Utilities
